isiter/LICENSE
isiter/README.MD
isiter/__init__.py
isiter/requirements.txt
isiter/thirdparty.json
isiter-0.10.dist-info/LICENSE.rst
isiter-0.10.dist-info/METADATA
isiter-0.10.dist-info/WHEEL
isiter-0.10.dist-info/top_level.txt
isiter-0.10.dist-info/RECORD
